Read_CSV.py
__init__.py
english.py
math.py
science.py
KavModule-0.0.1.dist-info/LICENSE
KavModule-0.0.1.dist-info/METADATA
KavModule-0.0.1.dist-info/WHEEL
KavModule-0.0.1.dist-info/top_level.txt
KavModule-0.0.1.dist-info/RECORD
